xcube_icosdp/__init__.py
xcube_icosdp/constants.py
xcube_icosdp/plugin.py
xcube_icosdp/preload.py
xcube_icosdp/store.py
xcube_icosdp/utils.py
xcube_icosdp/version.py
xcube_icosdp-0.1.0.dist-info/licenses/LICENSE
xcube_icosdp-0.1.0.dist-info/METADATA
xcube_icosdp-0.1.0.dist-info/WHEEL
xcube_icosdp-0.1.0.dist-info/top_level.txt
xcube_icosdp-0.1.0.dist-info/RECORD
