Metadata-Version: 2.4
Name: xcube-icosdp
Version: 0.1.0
Summary: A data store to access datasets from ICOS Data Portal.
Author: xcube Development Team
License: GPL-3.0-or-later
Project-URL: Documentation, https://github.com/xcube-dev/xcube-icosdp
Project-URL: Repository, https://github.com/xcube-dev/xcube-icosdp
Project-URL: Changelog, https://github.com/xcube-dev/xcube-icosdp/blob/main/CHANGES.md
Project-URL: Issues, https://github.com/xcube-dev/xcube-icosdp/issues
Keywords: xcube,ICOS,FLUXCOM-X-BASE,xarray,dask,parallel processing
Classifier: Development Status :: 5 - Production/Stable
Classifier: Intended Audience :: Science/Research
Classifier: Intended Audience :: Developers
Classifier: License :: OSI Approved :: Apache Software License
Classifier: Programming Language :: Python :: 3
Classifier: Programming Language :: Python :: 3.10
Classifier: Programming Language :: Python :: 3.11
Classifier: Programming Language :: Python :: 3.12
Classifier: Programming Language :: Python :: 3.13
Classifier: Topic :: Software Development
Classifier: Topic :: Scientific/Engineering
Classifier: Typing :: Typed
Classifier: Operating System :: Microsoft :: Windows
Classifier: Operating System :: POSIX
Classifier: Operating System :: Unix
Classifier: Operating System :: MacOS
Requires-Python: >=3.10
License-File: LICENSE
Requires-Dist: icoscp_core
Requires-Dist: numpy
Requires-Dist: pandas
Requires-Dist: xarray
Requires-Dist: xcube
Provides-Extra: dev
Requires-Dist: build; extra == "dev"
Requires-Dist: hatch; extra == "dev"
Requires-Dist: twine; extra == "dev"
Requires-Dist: black; extra == "dev"
Requires-Dist: isort; extra == "dev"
Requires-Dist: ruff; extra == "dev"
Requires-Dist: pytest; extra == "dev"
Requires-Dist: pytest-cov; extra == "dev"
Requires-Dist: jupyterlab; extra == "dev"
Requires-Dist: matplotlib; extra == "dev"
Provides-Extra: doc
Dynamic: license-file
